sas_frontend
